src/__init__.py
decipher_ua_agent.py
format_file_size.py
generate_analytical_output.py
nginx_log_stats.py
parse_line.py
parse_nginx_time_format.py
session_analysis.py
sessionize.py
sessions_from_ip.py
sort_by_body_size.py
unique_ips_only.py
nginx_log_stats-1.34.0.dist-info/LICENSE
nginx_log_stats-1.34.0.dist-info/METADATA
nginx_log_stats-1.34.0.dist-info/WHEEL
nginx_log_stats-1.34.0.dist-info/entry_points.txt
nginx_log_stats-1.34.0.dist-info/RECORD
